LICENSE
README.md
setup.cfg
setup.py
calendric_lib/__init__.py
calendric_lib.egg-info/PKG-INFO
calendric_lib.egg-info/SOURCES.txt
calendric_lib.egg-info/dependency_links.txt
calendric_lib.egg-info/requires.txt
calendric_lib.egg-info/top_level.txt