Metadata-Version: 2.1
Name: calendric-lib
Version: 0.0.9
Summary: Calendric-lib is a creative package for calendrical conversion operations in Python.
Home-page: https://github.com/saadbinmunir/Calendric-lib.git
Author: Saad Bin Munir
Author-email: saadmunir24@gmail.com
License: MIT
Platform: UNKNOWN
